[
  {
    "req_id": 1,
    "req_title": "The SW must manage requirements",
    "req_description": "Blablabla",
    "req_reference": "REQ-SYS-010",
    "req_category": "General",
    "req_applicability": "All Products",
    "req_current_status": "Accepted",
    "req_verification_method": "Inspection",
    "req_author": "Màrius Montón",
    "req_reviewer": "",
    "req_parent": null,
    "req_parent_title": "",
    "req_link": "None",
    "req_creation_date": "03-08-2025 08:50:30",
    "req_update_date": "03-08-2025 08:50:30",
    "req_deadline_date": "03-08-2025 08:50:30",
    "req_justification": null
  },
  {
    "req_id": 2,
    "req_title": "The SW must implement an API REST",
    "req_description": "API REST, blablabla",
    "req_reference": "REQ-API-010",
    "req_category": "API",
    "req_applicability": "All Products",
    "req_current_status": "Accepted",
    "req_verification_method": "Inspection",
    "req_author": "Màrius Montón",
    "req_reviewer": "",
    "req_parent": null,
    "req_parent_title": "",
    "req_link": "None",
    "req_creation_date": "03-08-2025 08:50:30",
    "req_update_date": "03-08-2025 08:50:30",
    "req_deadline_date": "03-08-2025 08:50:30",
    "req_justification": null
  },
  {
    "req_id": 3,
    "req_title": "The SW must implement a Web app",
    "req_description": "Web app",
    "req_reference": "REQ-SYS-020",
    "req_category": "System",
    "req_applicability": "All Products",
    "req_current_status": "Accepted",
    "req_verification_method": "Inspection",
    "req_author": "Màrius Montón",
    "req_reviewer": "",
    "req_parent": null,
    "req_parent_title": "",
    "req_link": "None",
    "req_creation_date": "03-08-2025 08:50:30",
    "req_update_date": "03-08-2025 08:50:30",
    "req_deadline_date": "03-08-2025 08:50:30",
    "req_justification": null
  },
  {
    "req_id": 4,
    "req_title": "The SW must export compliance matrix in excel format",
    "req_description": "Excel, blabla",
    "req_reference": "REQ-SYS-030",
    "req_category": "General",
    "req_applicability": "All Products",
    "req_current_status": "Accepted",
    "req_verification_method": "Inspection",
    "req_author": "Victor Martín",
    "req_reviewer": "",
    "req_parent": null,
    "req_parent_title": "",
    "req_link": "None",
    "req_creation_date": "03-08-2025 08:50:30",
    "req_update_date": "03-08-2025 08:50:30",
    "req_deadline_date": "03-08-2025 08:50:30",
    "req_justification": null
  }
]